claim.py
claim-1.0.0b1.dist-info/DESCRIPTION.rst
claim-1.0.0b1.dist-info/METADATA
claim-1.0.0b1.dist-info/RECORD
claim-1.0.0b1.dist-info/WHEEL
claim-1.0.0b1.dist-info/entry_points.txt
claim-1.0.0b1.dist-info/metadata.json
claim-1.0.0b1.dist-info/top_level.txt
