Metadata-Version: 2.0
Name: claim
Version: 1.0.0b1
Summary: A cli tool for converting file's line endings
Home-page: https://github.com/bukovyn/claim
Author: bukovyn
Author-email: bukovyn@gmail.com
License: UNKNOWN
